worek/__init__.py
worek/cli.py
worek/core.py
worek/exc.py
worek/utils.py
worek/version.py
worek/dialects/__init__.py
worek/dialects/postgres.py
worek/tests/__init__.py
worek/tests/conftest.py
worek/tests/helpers.py
worek/tests/test_cli.py
worek/tests/test_core.py
worek/tests/test_postgres.py
worek-0.1.1.dist-info/METADATA
worek-0.1.1.dist-info/WHEEL
worek-0.1.1.dist-info/entry_points.txt
worek-0.1.1.dist-info/top_level.txt
worek-0.1.1.dist-info/RECORD
