Metadata-Version: 2.1
Name: worek
Version: 0.1.1
Summary: Database Backup Command Line Utility
Home-page: https://github.com/level12/worek
Author: Nick Zaccardi
Author-email: nick.zaccardi@level12.io
License: BSD
Platform: UNKNOWN
Classifier: Development Status :: 4 - Beta
Classifier: Intended Audience :: Developers
Classifier: License :: OSI Approved :: BSD License
Classifier: Operating System :: OS Independent
Classifier: Programming Language :: Python :: 3.6
Requires-Dist: sqlalchemy
Requires-Dist: click
Requires-Dist: psycopg2-binary
Provides-Extra: ci
Requires-Dist: pytest; extra == 'ci'
Requires-Dist: pytest-cov; extra == 'ci'
Requires-Dist: flake8; extra == 'ci'
Requires-Dist: check-manifest; extra == 'ci'
Requires-Dist: docutils; extra == 'ci'
